{"name":"Threat: Snap Spinecrack","description":"Double-click to gain a large amount of bonus Mastery experience.\n<c=@Flavor>Help Amnoon earn the favor of Joko's armies by taking out notable threats.</c>","type":"Consumable","level":0,"rarity":"Exotic","vendor_value":0,"game_types":["PvpLobby","Wvw","Dungeon","Pve"],"flags":["AccountBound","Unique","AccountBindOnUse"],"restrictions":[],"id":84294,"chat_link":"[&AgFGSQEA]","icon":"https://render.guildwars2.com/file/26E72E049603550E4FCE4B560534CE284EC1336A/1861949.png","details":{"type":"Generic"}}